setup.py
ex8/__init__.py
ex8/hi.py
ex8.egg-info/PKG-INFO
ex8.egg-info/SOURCES.txt
ex8.egg-info/dependency_links.txt
ex8.egg-info/not-zip-safe
ex8.egg-info/top_level.txt