Metadata-Version: 1.0
Name: ex8
Version: 0.3
Summary: ex8 is going to take over
Home-page: http://github.com/ex8
Author: Matt M
Author-email: matt@puroxy.org
License: UNKNOWN
Platform: UNKNOWN
